{
  "attempt_status": "canonical",
  "book_or_collection": "Position Pieces for Cello, Book 1",
  "canonical_piece_id": "65f6647f-1aaf-4b26-a598-3a117f78c41c",
  "catalog_metadata": {
    "book_or_collection": "Position Pieces for Cello, Book 1",
    "composer": "Rick Mooney",
    "contained_piece_titles": [
      "Walking Home"
    ],
    "multi_piece_page": false,
    "primary_instrument": "Cello",
    "source_file_name": "9fae1a51-88c5-4110-9e9c-c6c3cb0b7bfc.pdf",
    "source_page_end": 56,
    "source_page_start": 56,
    "title": "Walking Home"
  },
  "catalog_suggestions": [
    {
      "confidence": 0.84,
      "fields": {
        "book_or_collection": "Position Pieces for Cello, Book 1",
        "composer": "Rick Mooney",
        "contained_piece_titles": [
          "Walking Home"
        ],
        "multi_piece_page": false,
        "primary_instrument": "Cello",
        "source_file_name": "9fae1a51-88c5-4110-9e9c-c6c3cb0b7bfc.pdf",
        "source_page_end": 56,
        "source_page_start": 56,
        "title": "Walking Home"
      },
      "source": "book_split_hint"
    }
  ],
  "composer": "Rick Mooney",
  "duplicate_attempt_count": 0,
  "logical_piece_key": "piece|book_sha256:8cef428183a3be697d28d69a450878038b556666a18aadb68483ace0e9b47dcc|pages:56-56|title:walking home|composer:rick mooney|instrument:cello",
  "normalized_composer": "rick mooney",
  "normalized_title": "walking home",
  "notes": null,
  "piece_kind": "piece",
  "previous_visible_to_profile_ids": [],
  "primary_instrument": "Cello",
  "processed_metadata": {
    "primary_instrument": "Cello"
  },
  "score_versions": {
    "5f56f104-6ff5-4f46-a695-94bfcee1f32f": {
      "approved_by_parent": true,
      "artifact_role": "original_import",
      "display_rank": 100,
      "student_default": false
    },
    "9c218a30-a4fb-4da6-be69-e88916d91242": {
      "approved_by_parent": false,
      "artifact_role": "cleaned_pdf",
      "display_rank": 10,
      "replaces_score_version_id": "5f56f104-6ff5-4f46-a695-94bfcee1f32f",
      "student_default": true
    }
  },
  "sort_composer": "rick mooney",
  "sort_title": "walking home",
  "source_book_fingerprint": "book_sha256:8cef428183a3be697d28d69a450878038b556666a18aadb68483ace0e9b47dcc",
  "source_book_id": "fa8de395-26c8-4d97-9aff-a20858953b44",
  "source_content_sha256": "88975d496a2d47dae800452611f86c24d5c8c8a2cf6ea4fa358f76603984d3cb",
  "source_page_end": 56,
  "source_page_start": 56,
  "split_confidence": 0.84,
  "title": "Walking Home",
  "validation_warnings": [],
  "visible_to_profile_ids": [],
  "workflow_closed": false
}